{
  "type": "minecraft:crafting_shapeless",
  "ingredients": [
    {
      "item": "minecraft:rotten_flesh"
    },
    {
      "item": "minecraft:rotten_flesh"
    },
    {
      "item": "minecraft:rotten_flesh"
    },
    {
      "tag": "forge:ingots/silver"
    },
    {
      "tag": "forge:ingots/silver"
    },
    {
      "item": "minecraft:ghast_tear"
    },
    {
      "item": "minecraft:ghast_tear"
    }
  ],
  "result": {
    "item": "caverns_and_chasms:sanguine_plating",
    "count": 1
  }
}